dbx_hpexts_bootstrap/__init__.py
dbx_hpexts_bootstrap-0.4.3.dist-info/LICENCE
dbx_hpexts_bootstrap-0.4.3.dist-info/METADATA
dbx_hpexts_bootstrap-0.4.3.dist-info/WHEEL
dbx_hpexts_bootstrap-0.4.3.dist-info/RECORD
