Metadata-Version: 2.1
Name: dbx-hpexts-bootstrap
Version: 0.4.3
Summary: Bootstrap that installs the private 'common' package from GitHub.
Author: francisco javier larios
Author-email: fjlsoto@gmail.com
Requires-Python: >=3.10,<4.0
Classifier: Programming Language :: Python :: 3
Classifier: Programming Language :: Python :: 3.10
Classifier: Programming Language :: Python :: 3.11
Classifier: Programming Language :: Python :: 3.12
Requires-Dist: packaging (>=23)
